{
	"next_topic_id": 2,
	"topic": [
		{
			"topic_id": 1,
			"title": "Seeders of Halo Page",
			"body": "Hey, I had issues with the TOR Integration, so I temp. disabled it. I got currently ~551 Seeders of the Helo Startpage, how many do you got with TOR enabled ?",
			"added": 1458985764
		}
	],
	"topic_vote": {},
	"next_comment_id": 2,
	"comment": {
		"4762_1KbV1e1u6P6AsY8XNBydgtbtN8iSB5WMyG": [
			{
				"comment_id": 1,
				"body": "I would have read it, if it where on Zeronet",
				"added": 1458985858
			}
		]
	},
	"comment_vote": {}
}