{
	"next_topic_id": 3,
	"topic": [
		{
			"topic_id": 1,
			"title": "Best way to invest in stock and what companies",
			"body": "I'd really appreciate if anyone would give me tips on this, thank you.\nDemiurge Out",
			"added": 1457610203
		},
		{
			"topic_id": 2,
			"title": "how to backup?",
			"body": "how to back up my data/user.json file?",
			"added": 1457610799
		}
	],
	"topic_vote": {
		"2_1LJMypJ67iEBwah82xwVVdB8SGZ1mwqgHQ": 1
	},
	"next_comment_id": 3,
	"comment": {
		"1_1AEFexfsUfegWprdXJ7b6xXmMt5P3m9EUv": [
			{
				"comment_id": 1,
				"body": "its not working fam",
				"added": 1457610337
			}
		],
		"2_1G1yCPeGqsu3Hv2w93MXyhW271WZUnBN4t": [
			{
				"comment_id": 2,
				"body": "> [erkan](#comment_31_1H8oKiRa7fGgUqS1hpUtaSYLvAqkaknbkf): on which OS are you?\n> in the simplest way, just copy that file elsewhere, so you can copy it backup\n\nwhere would i find it? im not good at this and i would really like some help... and im on windows 7",
				"added": 1457611128
			}
		]
	},
	"comment_vote": {}
}