{
	"next_topic_id": 2,
	"topic": [
		{
			"topic_id": 1,
			"title": "Salam here :)",
			"body": "",
			"added": 1456971504
		}
	],
	"topic_vote": {},
	"next_comment_id": 3,
	"comment": {
		"4_1PX7VW6xfccTT2tNUTwrYKJpGsGfrnoJfP": [
			{
				"comment_id": 1,
				"body": "If you want to complain about something with somebody, the something must be stored (history)somewhere.\nNow with Blockchain, nor you nor the somebody can modify what you have done together",
				"added": 1456971460
			}
		],
		"2_1J3rJ8ecnwH2EPYa6MrgZttBNc61ACFiCj": [
			{
				"comment_id": 2,
				"body": "wazaaaaaap",
				"added": 1456971487
			}
		]
	},
	"comment_vote": {}
}