{
	"next_topic_id": 1,
	"topic": [],
	"topic_vote": {},
	"next_comment_id": 3,
	"comment": {
		"2_1J3rJ8ecnwH2EPYa6MrgZttBNc61ACFiCj": [
			{
				"comment_id": 1,
				"body": "pussy",
				"added": 1461417681
			}
		],
		"1_18jipjDsfAxAuq4ixbi2w24xJrYVfTYFPn": [
			{
				"comment_id": 2,
				"body": "I don`t give a fuck, i can give you my real name, adress, ocupation etc. I don`t have nothing to hide. So FUCK THE NSA FUCK THE FBI BASTARDS ! Nothing to hide! Check me piece of shit! I use this for fun! And because i can and i know how to use! Why not! And i dont use with tor just my fking real ip.",
				"added": 1461420729
			}
		]
	},
	"comment_vote": {}
}